ssd1362/__init__.py
ssd1362/ssd1362.py
ssd1362_py-0.1.5.dist-info/DESCRIPTION.rst
ssd1362_py-0.1.5.dist-info/METADATA
ssd1362_py-0.1.5.dist-info/RECORD
ssd1362_py-0.1.5.dist-info/WHEEL
ssd1362_py-0.1.5.dist-info/metadata.json
ssd1362_py-0.1.5.dist-info/top_level.txt
