Metadata-Version: 2.0
Name: ssd1362-py
Version: 0.1.5
Summary: ssd1362 for python
Home-page: https://gitlab.com/telelian/peripheral-library/ssd1362.git
Author: mrzjo
Author-email: mrzjo05@gmail.com
License: UNKNOWN
Platform: UNKNOWN
Classifier: Development Status :: 4 - Beta
Classifier: Programming Language :: Python
Classifier: Programming Language :: Python :: 3
Classifier: Topic :: System :: Hardware
License-File: LICENSE
Requires-Dist: numpy (==1.18.1)
Requires-Dist: spidev (==3.4)
Requires-Dist: g4l (==0.1.3)
